clutta/__init__.py
clutta/constants.py
clutta/core.py
clutta/exceptions.py
clutta/helpers.py
clutta/pulse.py
clutta_py-0.0.1.dist-info/LICENSE
clutta_py-0.0.1.dist-info/METADATA
clutta_py-0.0.1.dist-info/WHEEL
clutta_py-0.0.1.dist-info/top_level.txt
clutta_py-0.0.1.dist-info/RECORD
