Metadata-Version: 2.2
Name: clutta-py
Version: 0.0.1
Summary: Clutta-py is the official Python SDK for interacting with Clutta, a platform for observability and monitoring.
Author: Sefas Technologies
Author-email: Sefas Technologies <support@clutta.io>
License: Copyright 2025 Sefas Technologies
License-File: LICENSE
Requires-Dist: python-dotenv
Requires-Dist: urllib3
Dynamic: author
